dectext/__init__.py
dectext/dec.py
dectext-0.5.dist-info/LICENSE.txt
dectext-0.5.dist-info/METADATA
dectext-0.5.dist-info/WHEEL
dectext-0.5.dist-info/entry_points.txt
dectext-0.5.dist-info/top_level.txt
dectext-0.5.dist-info/RECORD
