Metadata-Version: 2.1
Name: dectext
Version: 0.5
Summary: It print a decorated text on console.
Home-page: https://github.com/SaurabhGujjar/dectext.git
Author: Saurabh Gujjar
Author-email: saurabhpanwar127@gmail.com
License: MIT
Download-URL: https://github.com/SaurabhGujjar/dectext/archive/v_0.05.tar.gz
Keywords: TEXT,DECORATION,CONSOLE
Platform: UNKNOWN
Classifier: Development Status :: 3 - Alpha
Classifier: Intended Audience :: Developers
Classifier: Topic :: Software Development :: Build Tools
Classifier: License :: OSI Approved :: MIT License
Classifier: Programming Language :: Python :: 3
Classifier: Programming Language :: Python :: 3.8
Classifier: Programming Language :: Python :: 3.6
Classifier: Programming Language :: Python :: 3.7
Requires-Dist: Click
Requires-Dist: pyfiglet
Requires-Dist: random2
